buildtwine/__init__.py
buildtwine-0.1.0.dist-info/METADATA
buildtwine-0.1.0.dist-info/WHEEL
buildtwine-0.1.0.dist-info/top_level.txt
buildtwine-0.1.0.dist-info/RECORD
