Metadata-Version: 2.2
Name: buildtwine
Version: 0.1.0
Summary: A minimal example Python package
Requires-Python: >=3.6
